[
  {
    "type": "customer",
    "data": {
      "name": "dacchu",
      "age": 20,
      "email": "princevinay4700@gmail.com",
      "phone": "8310268127",
      "plan": "Monthly",
      "validity": "2026-01-23T00:00:00.000Z",
      "notes": "",
      "photo": "",
      "createdBy": "69476926f79a70314966ba12",
      "memberId": "U001",
      "password": "$2a$10$eTbL/UwmUXKWo8Iguc2h4eee6FjjVDjLuUO7oflPfzbMPo/HK3C4m",
      "isFirstLogin": true,
      "totalVisits": 0,
      "balance": 0,
      "badgesEarned": [],
      "isInside": false,
      "_id": "694a40bc47af918349188864",
      "createdAt": "2025-12-23T07:11:56.885Z",
      "updatedAt": "2025-12-23T07:11:56.885Z",
      "customerId": "cust_1766473917037_4e9zolbjr",
      "__v": 0,
      "status": "active",
      "daysRemaining": 31,
      "id": "694a40bc47af918349188864"
    },
    "timestamp": "2025-12-23T07:11:57.046Z"
  },
  {
    "type": "customer",
    "data": {
      "_id": "694a40bc47af918349188864",
      "name": "dacchu",
      "age": 20,
      "email": "princevinay4700@gmail.com",
      "phone": "8310268127",
      "plan": "Monthly",
      "validity": "2026-01-23T00:00:00.000Z",
      "notes": "",
      "photo": "",
      "createdBy": "69476926f79a70314966ba12",
      "memberId": "U001",
      "isFirstLogin": true,
      "totalVisits": 1,
      "balance": 0,
      "badgesEarned": [],
      "isInside": true,
      "createdAt": "2025-12-23T07:11:56.885Z",
      "updatedAt": "2025-12-23T07:23:31.545Z",
      "customerId": "cust_1766473917037_4e9zolbjr",
      "__v": 0,
      "lastActivity": "2025-12-23T07:23:31.544Z",
      "status": "active",
      "daysRemaining": 31,
      "id": "694a40bc47af918349188864"
    },
    "timestamp": "2025-12-23T07:23:31.549Z"
  },
  {
    "type": "attendance",
    "data": {
      "customerId": "694a40bc47af918349188864",
      "customerName": "dacchu",
      "date": "2025-12-23",
      "time": "12:53 PM",
      "timestamp": "2025-12-23T07:23:31.544Z",
      "membershipStatus": "active",
      "type": "IN",
      "deviceId": "mock-simulator",
      "_id": "694a437347af91834918893f",
      "createdAt": "2025-12-23T07:23:31.563Z",
      "attendanceId": "att_1766474611563_ze1bqqghp",
      "__v": 0
    },
    "timestamp": "2025-12-23T07:23:31.565Z"
  },
  {
    "type": "customer",
    "data": {
      "_id": "694a40bc47af918349188864",
      "name": "dacchu",
      "age": 20,
      "email": "princevinay4700@gmail.com",
      "phone": "8310268127",
      "plan": "Monthly",
      "validity": "2026-01-23T00:00:00.000Z",
      "notes": "",
      "photo": "",
      "createdBy": "69476926f79a70314966ba12",
      "memberId": "U001",
      "isFirstLogin": true,
      "totalVisits": 1,
      "balance": 0,
      "badgesEarned": [],
      "isInside": false,
      "createdAt": "2025-12-23T07:11:56.885Z",
      "updatedAt": "2025-12-23T07:23:48.452Z",
      "customerId": "cust_1766473917037_4e9zolbjr",
      "__v": 0,
      "lastActivity": "2025-12-23T07:23:48.451Z",
      "status": "active",
      "daysRemaining": 31,
      "id": "694a40bc47af918349188864"
    },
    "timestamp": "2025-12-23T07:23:48.454Z"
  },
  {
    "type": "attendance",
    "data": {
      "customerId": "694a40bc47af918349188864",
      "customerName": "dacchu",
      "date": "2025-12-23",
      "time": "12:53 PM",
      "timestamp": "2025-12-23T07:23:48.451Z",
      "membershipStatus": "active",
      "type": "OUT",
      "deviceId": "mock-simulator",
      "_id": "694a438447af918349188950",
      "createdAt": "2025-12-23T07:23:48.465Z",
      "attendanceId": "att_1766474628465_hx3hd3tc7",
      "__v": 0
    },
    "timestamp": "2025-12-23T07:23:48.467Z"
  },
  {
    "type": "customer",
    "data": {
      "_id": "694a40bc47af918349188864",
      "name": "dacchu",
      "age": 20,
      "email": "princevinay4700@gmail.com",
      "phone": "8310268127",
      "plan": "Monthly",
      "validity": "2026-01-23T00:00:00.000Z",
      "notes": "",
      "photo": "",
      "createdBy": "69476926f79a70314966ba12",
      "memberId": "U001",
      "isFirstLogin": true,
      "totalVisits": 2,
      "balance": 0,
      "badgesEarned": [],
      "isInside": true,
      "createdAt": "2025-12-23T07:11:56.885Z",
      "updatedAt": "2025-12-23T11:24:52.817Z",
      "customerId": "cust_1766473917037_4e9zolbjr",
      "__v": 0,
      "lastActivity": "2025-12-23T11:24:52.804Z",
      "status": "active",
      "daysRemaining": 31,
      "id": "694a40bc47af918349188864"
    },
    "timestamp": "2025-12-23T11:24:52.825Z"
  },
  {
    "type": "attendance",
    "data": {
      "customerId": "694a40bc47af918349188864",
      "customerName": "dacchu",
      "date": "2025-12-23",
      "time": "04:54 PM",
      "timestamp": "2025-12-23T11:24:52.804Z",
      "membershipStatus": "active",
      "type": "IN",
      "deviceId": "mock-simulator",
      "_id": "694a7c0446241301c385505a",
      "createdAt": "2025-12-23T11:24:52.839Z",
      "attendanceId": "att_1766489092839_5my2vujac",
      "__v": 0
    },
    "timestamp": "2025-12-23T11:24:52.845Z"
  },
  {
    "type": "customer",
    "data": {
      "_id": "694a40bc47af918349188864",
      "name": "dacchu",
      "age": 20,
      "email": "princevinay4700@gmail.com",
      "phone": "8310268127",
      "plan": "Monthly",
      "validity": "2026-01-23T00:00:00.000Z",
      "notes": "",
      "photo": "",
      "createdBy": "69476926f79a70314966ba12",
      "memberId": "U001",
      "isFirstLogin": true,
      "totalVisits": 2,
      "balance": 0,
      "badgesEarned": [],
      "isInside": false,
      "createdAt": "2025-12-23T07:11:56.885Z",
      "updatedAt": "2025-12-23T11:24:56.064Z",
      "customerId": "cust_1766473917037_4e9zolbjr",
      "__v": 0,
      "lastActivity": "2025-12-23T11:24:56.062Z",
      "status": "active",
      "daysRemaining": 31,
      "id": "694a40bc47af918349188864"
    },
    "timestamp": "2025-12-23T11:24:56.067Z"
  },
  {
    "type": "attendance",
    "data": {
      "customerId": "694a40bc47af918349188864",
      "customerName": "dacchu",
      "date": "2025-12-23",
      "time": "04:54 PM",
      "timestamp": "2025-12-23T11:24:56.062Z",
      "membershipStatus": "active",
      "type": "OUT",
      "deviceId": "mock-simulator",
      "_id": "694a7c0846241301c3855068",
      "createdAt": "2025-12-23T11:24:56.074Z",
      "attendanceId": "att_1766489096074_3oomnxceu",
      "__v": 0
    },
    "timestamp": "2025-12-23T11:24:56.078Z"
  },
  {
    "type": "customer",
    "data": {
      "_id": "694a40bc47af918349188864",
      "name": "dacchu",
      "age": 20,
      "email": "princevinay4700@gmail.com",
      "phone": "8310268127",
      "plan": "Monthly",
      "validity": "2026-01-23T00:00:00.000Z",
      "notes": "",
      "photo": "",
      "createdBy": "69476926f79a70314966ba12",
      "memberId": "U001",
      "isFirstLogin": true,
      "totalVisits": 2,
      "balance": 0,
      "badgesEarned": [],
      "isInside": false,
      "createdAt": "2025-12-23T07:11:56.885Z",
      "updatedAt": "2025-12-23T11:24:58.983Z",
      "customerId": "cust_1766473917037_4e9zolbjr",
      "__v": 0,
      "lastActivity": "2025-12-23T11:24:58.982Z",
      "status": "active",
      "daysRemaining": 31,
      "id": "694a40bc47af918349188864"
    },
    "timestamp": "2025-12-23T11:24:58.985Z"
  },
  {
    "type": "attendance",
    "data": {
      "customerId": "694a40bc47af918349188864",
      "customerName": "dacchu",
      "date": "2025-12-23",
      "time": "04:54 PM",
      "timestamp": "2025-12-23T11:24:58.982Z",
      "membershipStatus": "active",
      "type": "OUT",
      "deviceId": "mock-simulator",
      "_id": "694a7c0a46241301c3855075",
      "createdAt": "2025-12-23T11:24:58.990Z",
      "attendanceId": "att_1766489098990_hxymna7cq",
      "__v": 0
    },
    "timestamp": "2025-12-23T11:24:58.992Z"
  },
  {
    "type": "customer",
    "data": {
      "_id": "694a40bc47af918349188864",
      "name": "dacchu",
      "age": 20,
      "email": "princevinay4700@gmail.com",
      "phone": "8310268127",
      "plan": "Monthly",
      "validity": "2026-01-23T00:00:00.000Z",
      "notes": "",
      "photo": "",
      "createdBy": "69476926f79a70314966ba12",
      "memberId": "U001",
      "isFirstLogin": true,
      "totalVisits": 2,
      "balance": 0,
      "badgesEarned": [],
      "isInside": false,
      "createdAt": "2025-12-23T07:11:56.885Z",
      "updatedAt": "2025-12-23T11:24:59.150Z",
      "customerId": "cust_1766473917037_4e9zolbjr",
      "__v": 0,
      "lastActivity": "2025-12-23T11:24:59.148Z",
      "status": "active",
      "daysRemaining": 31,
      "id": "694a40bc47af918349188864"
    },
    "timestamp": "2025-12-23T11:24:59.152Z"
  },
  {
    "type": "attendance",
    "data": {
      "customerId": "694a40bc47af918349188864",
      "customerName": "dacchu",
      "date": "2025-12-23",
      "time": "04:54 PM",
      "timestamp": "2025-12-23T11:24:59.148Z",
      "membershipStatus": "active",
      "type": "OUT",
      "deviceId": "mock-simulator",
      "_id": "694a7c0b46241301c385507a",
      "createdAt": "2025-12-23T11:24:59.157Z",
      "attendanceId": "att_1766489099157_ykmhmno8f",
      "__v": 0
    },
    "timestamp": "2025-12-23T11:24:59.160Z"
  },
  {
    "type": "customer",
    "data": {
      "_id": "694a40bc47af918349188864",
      "name": "dacchu",
      "age": 20,
      "email": "princevinay4700@gmail.com",
      "phone": "8310268127",
      "plan": "Monthly",
      "validity": "2026-01-23T00:00:00.000Z",
      "notes": "",
      "photo": "",
      "createdBy": "69476926f79a70314966ba12",
      "memberId": "U001",
      "isFirstLogin": true,
      "totalVisits": 2,
      "balance": 0,
      "badgesEarned": [],
      "isInside": false,
      "createdAt": "2025-12-23T07:11:56.885Z",
      "updatedAt": "2025-12-23T11:24:59.315Z",
      "customerId": "cust_1766473917037_4e9zolbjr",
      "__v": 0,
      "lastActivity": "2025-12-23T11:24:59.314Z",
      "status": "active",
      "daysRemaining": 31,
      "id": "694a40bc47af918349188864"
    },
    "timestamp": "2025-12-23T11:24:59.318Z"
  },
  {
    "type": "attendance",
    "data": {
      "customerId": "694a40bc47af918349188864",
      "customerName": "dacchu",
      "date": "2025-12-23",
      "time": "04:54 PM",
      "timestamp": "2025-12-23T11:24:59.314Z",
      "membershipStatus": "active",
      "type": "OUT",
      "deviceId": "mock-simulator",
      "_id": "694a7c0b46241301c385507f",
      "createdAt": "2025-12-23T11:24:59.323Z",
      "attendanceId": "att_1766489099323_tc4g5w7w2",
      "__v": 0
    },
    "timestamp": "2025-12-23T11:24:59.326Z"
  },
  {
    "type": "customer",
    "data": {
      "_id": "694a40bc47af918349188864",
      "name": "dacchu",
      "age": 20,
      "email": "princevinay4700@gmail.com",
      "phone": "8310268127",
      "plan": "Monthly",
      "validity": "2026-01-23T00:00:00.000Z",
      "notes": "",
      "photo": "",
      "createdBy": "69476926f79a70314966ba12",
      "memberId": "U001",
      "isFirstLogin": true,
      "totalVisits": 2,
      "balance": 0,
      "badgesEarned": [],
      "isInside": false,
      "createdAt": "2025-12-23T07:11:56.885Z",
      "updatedAt": "2025-12-23T11:24:59.464Z",
      "customerId": "cust_1766473917037_4e9zolbjr",
      "__v": 0,
      "lastActivity": "2025-12-23T11:24:59.463Z",
      "status": "active",
      "daysRemaining": 31,
      "id": "694a40bc47af918349188864"
    },
    "timestamp": "2025-12-23T11:24:59.466Z"
  },
  {
    "type": "attendance",
    "data": {
      "customerId": "694a40bc47af918349188864",
      "customerName": "dacchu",
      "date": "2025-12-23",
      "time": "04:54 PM",
      "timestamp": "2025-12-23T11:24:59.463Z",
      "membershipStatus": "active",
      "type": "OUT",
      "deviceId": "mock-simulator",
      "_id": "694a7c0b46241301c3855084",
      "createdAt": "2025-12-23T11:24:59.470Z",
      "attendanceId": "att_1766489099470_0t66utxio",
      "__v": 0
    },
    "timestamp": "2025-12-23T11:24:59.471Z"
  },
  {
    "type": "customer",
    "data": {
      "_id": "694a40bc47af918349188864",
      "name": "dacchu",
      "age": 20,
      "email": "princevinay4700@gmail.com",
      "phone": "8310268127",
      "plan": "Monthly",
      "validity": "2026-01-23T00:00:00.000Z",
      "notes": "",
      "photo": "",
      "createdBy": "69476926f79a70314966ba12",
      "memberId": "U001",
      "isFirstLogin": true,
      "totalVisits": 2,
      "balance": 0,
      "badgesEarned": [],
      "isInside": false,
      "createdAt": "2025-12-23T07:11:56.885Z",
      "updatedAt": "2025-12-23T11:24:59.631Z",
      "customerId": "cust_1766473917037_4e9zolbjr",
      "__v": 0,
      "lastActivity": "2025-12-23T11:24:59.630Z",
      "status": "active",
      "daysRemaining": 31,
      "id": "694a40bc47af918349188864"
    },
    "timestamp": "2025-12-23T11:24:59.633Z"
  },
  {
    "type": "attendance",
    "data": {
      "customerId": "694a40bc47af918349188864",
      "customerName": "dacchu",
      "date": "2025-12-23",
      "time": "04:54 PM",
      "timestamp": "2025-12-23T11:24:59.630Z",
      "membershipStatus": "active",
      "type": "OUT",
      "deviceId": "mock-simulator",
      "_id": "694a7c0b46241301c3855089",
      "createdAt": "2025-12-23T11:24:59.638Z",
      "attendanceId": "att_1766489099638_6zjpy6bk9",
      "__v": 0
    },
    "timestamp": "2025-12-23T11:24:59.641Z"
  },
  {
    "type": "customer",
    "data": {
      "_id": "694a40bc47af918349188864",
      "name": "dacchu",
      "age": 20,
      "email": "princevinay4700@gmail.com",
      "phone": "8310268127",
      "plan": "Monthly",
      "validity": "2026-01-23T00:00:00.000Z",
      "notes": "",
      "photo": "",
      "createdBy": "69476926f79a70314966ba12",
      "memberId": "U001",
      "isFirstLogin": true,
      "totalVisits": 2,
      "balance": 0,
      "badgesEarned": [],
      "isInside": false,
      "createdAt": "2025-12-23T07:11:56.885Z",
      "updatedAt": "2025-12-23T11:24:59.779Z",
      "customerId": "cust_1766473917037_4e9zolbjr",
      "__v": 0,
      "lastActivity": "2025-12-23T11:24:59.778Z",
      "status": "active",
      "daysRemaining": 31,
      "id": "694a40bc47af918349188864"
    },
    "timestamp": "2025-12-23T11:24:59.781Z"
  },
  {
    "type": "attendance",
    "data": {
      "customerId": "694a40bc47af918349188864",
      "customerName": "dacchu",
      "date": "2025-12-23",
      "time": "04:54 PM",
      "timestamp": "2025-12-23T11:24:59.778Z",
      "membershipStatus": "active",
      "type": "OUT",
      "deviceId": "mock-simulator",
      "_id": "694a7c0b46241301c385508e",
      "createdAt": "2025-12-23T11:24:59.784Z",
      "attendanceId": "att_1766489099784_eipgqsw2s",
      "__v": 0
    },
    "timestamp": "2025-12-23T11:24:59.786Z"
  },
  {
    "type": "customer",
    "data": {
      "_id": "694a40bc47af918349188864",
      "name": "dacchu",
      "age": 20,
      "email": "princevinay4700@gmail.com",
      "phone": "8310268127",
      "plan": "Monthly",
      "validity": "2026-01-23T00:00:00.000Z",
      "notes": "",
      "photo": "",
      "createdBy": "69476926f79a70314966ba12",
      "memberId": "U001",
      "isFirstLogin": true,
      "totalVisits": 2,
      "balance": 0,
      "badgesEarned": [],
      "isInside": false,
      "createdAt": "2025-12-23T07:11:56.885Z",
      "updatedAt": "2025-12-23T11:24:59.930Z",
      "customerId": "cust_1766473917037_4e9zolbjr",
      "__v": 0,
      "lastActivity": "2025-12-23T11:24:59.929Z",
      "status": "active",
      "daysRemaining": 31,
      "id": "694a40bc47af918349188864"
    },
    "timestamp": "2025-12-23T11:24:59.932Z"
  },
  {
    "type": "attendance",
    "data": {
      "customerId": "694a40bc47af918349188864",
      "customerName": "dacchu",
      "date": "2025-12-23",
      "time": "04:54 PM",
      "timestamp": "2025-12-23T11:24:59.929Z",
      "membershipStatus": "active",
      "type": "OUT",
      "deviceId": "mock-simulator",
      "_id": "694a7c0b46241301c3855093",
      "createdAt": "2025-12-23T11:24:59.937Z",
      "attendanceId": "att_1766489099937_kgl1rmja9",
      "__v": 0
    },
    "timestamp": "2025-12-23T11:24:59.939Z"
  },
  {
    "type": "customer",
    "data": {
      "_id": "694a40bc47af918349188864",
      "name": "dacchu",
      "age": 20,
      "email": "princevinay4700@gmail.com",
      "phone": "8310268127",
      "plan": "Monthly",
      "validity": "2026-01-23T00:00:00.000Z",
      "notes": "",
      "photo": "",
      "createdBy": "69476926f79a70314966ba12",
      "memberId": "U001",
      "isFirstLogin": true,
      "totalVisits": 2,
      "balance": 0,
      "badgesEarned": [],
      "isInside": false,
      "createdAt": "2025-12-23T07:11:56.885Z",
      "updatedAt": "2025-12-23T11:25:00.081Z",
      "customerId": "cust_1766473917037_4e9zolbjr",
      "__v": 0,
      "lastActivity": "2025-12-23T11:25:00.080Z",
      "status": "active",
      "daysRemaining": 31,
      "id": "694a40bc47af918349188864"
    },
    "timestamp": "2025-12-23T11:25:00.083Z"
  },
  {
    "type": "attendance",
    "data": {
      "customerId": "694a40bc47af918349188864",
      "customerName": "dacchu",
      "date": "2025-12-23",
      "time": "04:55 PM",
      "timestamp": "2025-12-23T11:25:00.080Z",
      "membershipStatus": "active",
      "type": "OUT",
      "deviceId": "mock-simulator",
      "_id": "694a7c0c46241301c3855098",
      "createdAt": "2025-12-23T11:25:00.087Z",
      "attendanceId": "att_1766489100087_r7qenpqf7",
      "__v": 0
    },
    "timestamp": "2025-12-23T11:25:00.089Z"
  },
  {
    "type": "customer",
    "data": {
      "_id": "694a40bc47af918349188864",
      "name": "dacchu",
      "age": 20,
      "email": "princevinay4700@gmail.com",
      "phone": "8310268127",
      "plan": "Monthly",
      "validity": "2026-01-23T00:00:00.000Z",
      "notes": "",
      "photo": "",
      "createdBy": "69476926f79a70314966ba12",
      "memberId": "U001",
      "isFirstLogin": true,
      "totalVisits": 3,
      "balance": 0,
      "badgesEarned": [],
      "isInside": true,
      "createdAt": "2025-12-23T07:11:56.885Z",
      "updatedAt": "2025-12-23T11:25:39.380Z",
      "customerId": "cust_1766473917037_4e9zolbjr",
      "__v": 0,
      "lastActivity": "2025-12-23T11:25:39.379Z",
      "status": "active",
      "daysRemaining": 31,
      "id": "694a40bc47af918349188864"
    },
    "timestamp": "2025-12-23T11:25:39.381Z"
  },
  {
    "type": "attendance",
    "data": {
      "customerId": "694a40bc47af918349188864",
      "customerName": "dacchu",
      "date": "2025-12-23",
      "time": "04:55 PM",
      "timestamp": "2025-12-23T11:25:39.379Z",
      "membershipStatus": "active",
      "type": "IN",
      "deviceId": "mock-simulator",
      "_id": "694a7c3346241301c38550e0",
      "createdAt": "2025-12-23T11:25:39.392Z",
      "attendanceId": "att_1766489139392_9eetrrhwm",
      "__v": 0
    },
    "timestamp": "2025-12-23T11:25:39.394Z"
  },
  {
    "type": "customer",
    "data": {
      "_id": "694a40bc47af918349188864",
      "name": "dacchu",
      "age": 20,
      "email": "princevinay4700@gmail.com",
      "phone": "8310268127",
      "plan": "Monthly",
      "validity": "2026-01-23T00:00:00.000Z",
      "notes": "",
      "photo": "",
      "createdBy": "69476926f79a70314966ba12",
      "memberId": "U001",
      "isFirstLogin": true,
      "totalVisits": 3,
      "balance": 0,
      "badgesEarned": [],
      "isInside": false,
      "createdAt": "2025-12-23T07:11:56.885Z",
      "updatedAt": "2025-12-23T11:25:44.191Z",
      "customerId": "cust_1766473917037_4e9zolbjr",
      "__v": 0,
      "lastActivity": "2025-12-23T11:25:44.190Z",
      "status": "active",
      "daysRemaining": 31,
      "id": "694a40bc47af918349188864"
    },
    "timestamp": "2025-12-23T11:25:44.192Z"
  },
  {
    "type": "attendance",
    "data": {
      "customerId": "694a40bc47af918349188864",
      "customerName": "dacchu",
      "date": "2025-12-23",
      "time": "04:55 PM",
      "timestamp": "2025-12-23T11:25:44.190Z",
      "membershipStatus": "active",
      "type": "OUT",
      "deviceId": "mock-simulator",
      "_id": "694a7c3846241301c38550f1",
      "createdAt": "2025-12-23T11:25:44.199Z",
      "attendanceId": "att_1766489144199_hmx3exakc",
      "__v": 0
    },
    "timestamp": "2025-12-23T11:25:44.202Z"
  },
  {
    "type": "customer",
    "data": {
      "_id": "694a40bc47af918349188864",
      "name": "dacchu",
      "age": 20,
      "email": "princevinay4700@gmail.com",
      "phone": "8310268127",
      "plan": "Monthly",
      "validity": "2026-01-23T00:00:00.000Z",
      "notes": "",
      "photo": "",
      "createdBy": "69476926f79a70314966ba12",
      "memberId": "U001",
      "isFirstLogin": true,
      "totalVisits": 4,
      "balance": 0,
      "badgesEarned": [],
      "isInside": true,
      "createdAt": "2025-12-23T07:11:56.885Z",
      "updatedAt": "2025-12-23T11:26:18.402Z",
      "customerId": "cust_1766473917037_4e9zolbjr",
      "__v": 0,
      "lastActivity": "2025-12-23T11:26:18.401Z",
      "status": "active",
      "daysRemaining": 31,
      "id": "694a40bc47af918349188864"
    },
    "timestamp": "2025-12-23T11:26:18.404Z"
  },
  {
    "type": "attendance",
    "data": {
      "customerId": "694a40bc47af918349188864",
      "customerName": "dacchu",
      "date": "2025-12-23",
      "time": "04:56 PM",
      "timestamp": "2025-12-23T11:26:18.401Z",
      "membershipStatus": "active",
      "type": "IN",
      "deviceId": "mock-simulator",
      "_id": "694a7c5a46241301c3855101",
      "createdAt": "2025-12-23T11:26:18.411Z",
      "attendanceId": "att_1766489178412_ig9qg163o",
      "__v": 0
    },
    "timestamp": "2025-12-23T11:26:18.413Z"
  },
  {
    "type": "customer",
    "data": {
      "_id": "694a40bc47af918349188864",
      "name": "dacchu",
      "age": 20,
      "email": "princevinay4700@gmail.com",
      "phone": "8310268127",
      "plan": "Monthly",
      "validity": "2026-01-23T00:00:00.000Z",
      "notes": "",
      "photo": "",
      "createdBy": "69476926f79a70314966ba12",
      "memberId": "U001",
      "isFirstLogin": true,
      "totalVisits": 4,
      "balance": 0,
      "badgesEarned": [],
      "isInside": false,
      "createdAt": "2025-12-23T07:11:56.885Z",
      "updatedAt": "2025-12-23T11:26:23.516Z",
      "customerId": "cust_1766473917037_4e9zolbjr",
      "__v": 0,
      "lastActivity": "2025-12-23T11:26:23.515Z",
      "status": "active",
      "daysRemaining": 31,
      "id": "694a40bc47af918349188864"
    },
    "timestamp": "2025-12-23T11:26:23.518Z"
  },
  {
    "type": "attendance",
    "data": {
      "customerId": "694a40bc47af918349188864",
      "customerName": "dacchu",
      "date": "2025-12-23",
      "time": "04:56 PM",
      "timestamp": "2025-12-23T11:26:23.515Z",
      "membershipStatus": "active",
      "type": "OUT",
      "deviceId": "mock-simulator",
      "_id": "694a7c5f46241301c385510f",
      "createdAt": "2025-12-23T11:26:23.525Z",
      "attendanceId": "att_1766489183525_yx2tanf4j",
      "__v": 0
    },
    "timestamp": "2025-12-23T11:26:23.527Z"
  },
  {
    "type": "customer",
    "data": {
      "_id": "694a40bc47af918349188864",
      "name": "dacchu",
      "age": 20,
      "email": "princevinay4700@gmail.com",
      "phone": "8310268127",
      "plan": "Monthly",
      "validity": "2026-01-23T00:00:00.000Z",
      "notes": "",
      "photo": "",
      "createdBy": "69476926f79a70314966ba12",
      "memberId": "U001",
      "isFirstLogin": true,
      "totalVisits": 5,
      "balance": 0,
      "badgesEarned": [],
      "isInside": true,
      "createdAt": "2025-12-23T07:11:56.885Z",
      "updatedAt": "2025-12-23T11:26:47.823Z",
      "customerId": "cust_1766473917037_4e9zolbjr",
      "__v": 0,
      "lastActivity": "2025-12-23T11:26:47.822Z",
      "status": "active",
      "daysRemaining": 31,
      "id": "694a40bc47af918349188864"
    },
    "timestamp": "2025-12-23T11:26:47.825Z"
  },
  {
    "type": "attendance",
    "data": {
      "customerId": "694a40bc47af918349188864",
      "customerName": "dacchu",
      "date": "2025-12-23",
      "time": "04:56 PM",
      "timestamp": "2025-12-23T11:26:47.822Z",
      "membershipStatus": "active",
      "type": "IN",
      "deviceId": "mock-simulator",
      "_id": "694a7c7746241301c385511f",
      "createdAt": "2025-12-23T11:26:47.834Z",
      "attendanceId": "att_1766489207834_0a9zuwydx",
      "__v": 0
    },
    "timestamp": "2025-12-23T11:26:47.836Z"
  },
  {
    "type": "customer",
    "data": {
      "_id": "694a40bc47af918349188864",
      "name": "dacchu",
      "age": 20,
      "email": "princevinay4700@gmail.com",
      "phone": "8310268127",
      "plan": "Monthly",
      "validity": "2026-01-23T00:00:00.000Z",
      "notes": "",
      "photo": "",
      "createdBy": "69476926f79a70314966ba12",
      "memberId": "U001",
      "isFirstLogin": true,
      "totalVisits": 5,
      "balance": 0,
      "badgesEarned": [],
      "isInside": false,
      "createdAt": "2025-12-23T07:11:56.885Z",
      "updatedAt": "2025-12-23T11:26:52.684Z",
      "customerId": "cust_1766473917037_4e9zolbjr",
      "__v": 0,
      "lastActivity": "2025-12-23T11:26:52.684Z",
      "status": "active",
      "daysRemaining": 31,
      "id": "694a40bc47af918349188864"
    },
    "timestamp": "2025-12-23T11:26:52.686Z"
  },
  {
    "type": "attendance",
    "data": {
      "customerId": "694a40bc47af918349188864",
      "customerName": "dacchu",
      "date": "2025-12-23",
      "time": "04:56 PM",
      "timestamp": "2025-12-23T11:26:52.684Z",
      "membershipStatus": "active",
      "type": "OUT",
      "deviceId": "mock-simulator",
      "_id": "694a7c7c46241301c385512d",
      "createdAt": "2025-12-23T11:26:52.693Z",
      "attendanceId": "att_1766489212693_s530ji4eo",
      "__v": 0
    },
    "timestamp": "2025-12-23T11:26:52.696Z"
  },
  {
    "type": "customer",
    "data": {
      "_id": "694a40bc47af918349188864",
      "name": "dacchu",
      "age": 20,
      "email": "princevinay4700@gmail.com",
      "phone": "8310268127",
      "plan": "Monthly",
      "validity": "2026-01-23T00:00:00.000Z",
      "notes": "",
      "photo": "",
      "createdBy": "69476926f79a70314966ba12",
      "memberId": "U001",
      "isFirstLogin": true,
      "totalVisits": 6,
      "balance": 0,
      "badgesEarned": [],
      "isInside": true,
      "createdAt": "2025-12-23T07:11:56.885Z",
      "updatedAt": "2025-12-23T11:32:08.312Z",
      "customerId": "cust_1766473917037_4e9zolbjr",
      "__v": 0,
      "lastActivity": "2025-12-23T11:32:08.312Z",
      "status": "active",
      "daysRemaining": 31,
      "id": "694a40bc47af918349188864"
    },
    "timestamp": "2025-12-23T11:32:08.314Z"
  },
  {
    "type": "attendance",
    "data": {
      "customerId": "694a40bc47af918349188864",
      "customerName": "dacchu",
      "date": "2025-12-23",
      "time": "05:02 PM",
      "timestamp": "2025-12-23T11:32:08.312Z",
      "membershipStatus": "active",
      "type": "IN",
      "deviceId": "mock-simulator",
      "_id": "694a7db846241301c3855152",
      "createdAt": "2025-12-23T11:32:08.322Z",
      "attendanceId": "att_1766489528322_bt0k5elr6",
      "__v": 0
    },
    "timestamp": "2025-12-23T11:32:08.328Z"
  },
  {
    "type": "customer",
    "data": {
      "_id": "694a40bc47af918349188864",
      "name": "dacchu",
      "age": 20,
      "email": "princevinay4700@gmail.com",
      "phone": "8310268127",
      "plan": "Monthly",
      "validity": "2026-01-23T00:00:00.000Z",
      "notes": "",
      "photo": "",
      "createdBy": "69476926f79a70314966ba12",
      "memberId": "U001",
      "isFirstLogin": true,
      "totalVisits": 6,
      "balance": 0,
      "badgesEarned": [],
      "isInside": false,
      "createdAt": "2025-12-23T07:11:56.885Z",
      "updatedAt": "2025-12-23T11:32:13.129Z",
      "customerId": "cust_1766473917037_4e9zolbjr",
      "__v": 0,
      "lastActivity": "2025-12-23T11:32:13.128Z",
      "status": "active",
      "daysRemaining": 31,
      "id": "694a40bc47af918349188864"
    },
    "timestamp": "2025-12-23T11:32:13.130Z"
  },
  {
    "type": "attendance",
    "data": {
      "customerId": "694a40bc47af918349188864",
      "customerName": "dacchu",
      "date": "2025-12-23",
      "time": "05:02 PM",
      "timestamp": "2025-12-23T11:32:13.128Z",
      "membershipStatus": "active",
      "type": "OUT",
      "deviceId": "mock-simulator",
      "_id": "694a7dbd46241301c3855163",
      "createdAt": "2025-12-23T11:32:13.136Z",
      "attendanceId": "att_1766489533136_v19kcdoh1",
      "__v": 0
    },
    "timestamp": "2025-12-23T11:32:13.138Z"
  },
  {
    "type": "customer",
    "data": {
      "_id": "694a40bc47af918349188864",
      "name": "dacchu",
      "age": 20,
      "email": "princevinay4700@gmail.com",
      "phone": "8310268127",
      "plan": "Monthly",
      "validity": "2026-01-23T00:00:00.000Z",
      "notes": "",
      "photo": "",
      "createdBy": "69476926f79a70314966ba12",
      "memberId": "U001",
      "isFirstLogin": true,
      "totalVisits": 7,
      "balance": 0,
      "badgesEarned": [],
      "isInside": true,
      "createdAt": "2025-12-23T07:11:56.885Z",
      "updatedAt": "2025-12-23T11:33:29.112Z",
      "customerId": "cust_1766473917037_4e9zolbjr",
      "__v": 0,
      "lastActivity": "2025-12-23T11:33:29.111Z",
      "status": "active",
      "daysRemaining": 31,
      "id": "694a40bc47af918349188864"
    },
    "timestamp": "2025-12-23T11:33:29.116Z"
  },
  {
    "type": "attendance",
    "data": {
      "customerId": "694a40bc47af918349188864",
      "customerName": "dacchu",
      "date": "2025-12-23",
      "time": "05:03 PM",
      "timestamp": "2025-12-23T11:33:29.111Z",
      "membershipStatus": "active",
      "type": "IN",
      "deviceId": "mock-simulator",
      "_id": "694a7e0946241301c385517f",
      "createdAt": "2025-12-23T11:33:29.123Z",
      "attendanceId": "att_1766489609123_cf4grsl6j",
      "__v": 0
    },
    "timestamp": "2025-12-23T11:33:29.125Z"
  },
  {
    "type": "customer",
    "data": {
      "_id": "694a40bc47af918349188864",
      "name": "dacchu",
      "age": 20,
      "email": "princevinay4700@gmail.com",
      "phone": "8310268127",
      "plan": "Monthly",
      "validity": "2026-01-23T00:00:00.000Z",
      "notes": "",
      "photo": "",
      "createdBy": "69476926f79a70314966ba12",
      "memberId": "U001",
      "isFirstLogin": true,
      "totalVisits": 7,
      "balance": 0,
      "badgesEarned": [],
      "isInside": false,
      "createdAt": "2025-12-23T07:11:56.885Z",
      "updatedAt": "2025-12-23T11:33:35.306Z",
      "customerId": "cust_1766473917037_4e9zolbjr",
      "__v": 0,
      "lastActivity": "2025-12-23T11:33:35.305Z",
      "status": "active",
      "daysRemaining": 31,
      "id": "694a40bc47af918349188864"
    },
    "timestamp": "2025-12-23T11:33:35.307Z"
  },
  {
    "type": "attendance",
    "data": {
      "customerId": "694a40bc47af918349188864",
      "customerName": "dacchu",
      "date": "2025-12-23",
      "time": "05:03 PM",
      "timestamp": "2025-12-23T11:33:35.305Z",
      "membershipStatus": "active",
      "type": "OUT",
      "deviceId": "mock-simulator",
      "_id": "694a7e0f46241301c3855196",
      "createdAt": "2025-12-23T11:33:35.316Z",
      "attendanceId": "att_1766489615316_kx64fmt2p",
      "__v": 0
    },
    "timestamp": "2025-12-23T11:33:35.320Z"
  },
  {
    "type": "customer",
    "data": {
      "_id": "694a40bc47af918349188864",
      "name": "dacchu",
      "age": 20,
      "email": "princevinay4700@gmail.com",
      "phone": "8310268127",
      "plan": "Monthly",
      "validity": "2026-01-23T00:00:00.000Z",
      "notes": "",
      "photo": "",
      "createdBy": "69476926f79a70314966ba12",
      "memberId": "U001",
      "isFirstLogin": true,
      "totalVisits": 8,
      "balance": 0,
      "badgesEarned": [],
      "isInside": true,
      "createdAt": "2025-12-23T07:11:56.885Z",
      "updatedAt": "2025-12-23T11:34:11.914Z",
      "customerId": "cust_1766473917037_4e9zolbjr",
      "__v": 0,
      "lastActivity": "2025-12-23T11:34:11.912Z",
      "status": "active",
      "daysRemaining": 31,
      "id": "694a40bc47af918349188864"
    },
    "timestamp": "2025-12-23T11:34:11.915Z"
  },
  {
    "type": "attendance",
    "data": {
      "customerId": "694a40bc47af918349188864",
      "customerName": "dacchu",
      "date": "2025-12-23",
      "time": "05:04 PM",
      "timestamp": "2025-12-23T11:34:11.912Z",
      "membershipStatus": "active",
      "type": "IN",
      "deviceId": "mock-simulator",
      "_id": "694a7e3346241301c38551af",
      "createdAt": "2025-12-23T11:34:11.924Z",
      "attendanceId": "att_1766489651924_r1g9s1jtp",
      "__v": 0
    },
    "timestamp": "2025-12-23T11:34:11.926Z"
  },
  {
    "type": "customer",
    "data": {
      "_id": "694a40bc47af918349188864",
      "name": "dacchu",
      "age": 20,
      "email": "princevinay4700@gmail.com",
      "phone": "8310268127",
      "plan": "Monthly",
      "validity": "2026-01-23T00:00:00.000Z",
      "notes": "",
      "photo": "",
      "createdBy": "69476926f79a70314966ba12",
      "memberId": "U001",
      "isFirstLogin": true,
      "totalVisits": 8,
      "balance": 0,
      "badgesEarned": [],
      "isInside": false,
      "createdAt": "2025-12-23T07:11:56.885Z",
      "updatedAt": "2025-12-23T11:35:11.930Z",
      "customerId": "cust_1766473917037_4e9zolbjr",
      "__v": 0,
      "lastActivity": "2025-12-23T11:35:11.928Z",
      "status": "active",
      "daysRemaining": 31,
      "id": "694a40bc47af918349188864"
    },
    "timestamp": "2025-12-23T11:35:11.932Z"
  },
  {
    "type": "attendance",
    "data": {
      "customerId": "694a40bc47af918349188864",
      "customerName": "dacchu",
      "date": "2025-12-23",
      "time": "05:05 PM",
      "timestamp": "2025-12-23T11:35:11.928Z",
      "membershipStatus": "active",
      "type": "OUT",
      "deviceId": "mock-simulator",
      "_id": "694a7e6f46241301c38551ce",
      "createdAt": "2025-12-23T11:35:11.945Z",
      "attendanceId": "att_1766489711945_1i7u2kss1",
      "__v": 0
    },
    "timestamp": "2025-12-23T11:35:11.947Z"
  },
  {
    "type": "customer",
    "data": {
      "_id": "694a40bc47af918349188864",
      "name": "dacchu",
      "age": 20,
      "email": "princevinay4700@gmail.com",
      "phone": "8310268127",
      "plan": "Monthly",
      "validity": "2026-01-23T00:00:00.000Z",
      "notes": "",
      "photo": "",
      "createdBy": "69476926f79a70314966ba12",
      "memberId": "U001",
      "isFirstLogin": true,
      "totalVisits": 9,
      "balance": 0,
      "badgesEarned": [],
      "isInside": true,
      "createdAt": "2025-12-23T07:11:56.885Z",
      "updatedAt": "2025-12-24T03:35:39.146Z",
      "customerId": "cust_1766473917037_4e9zolbjr",
      "__v": 0,
      "lastActivity": "2025-12-24T03:35:39.129Z",
      "status": "active",
      "daysRemaining": 30,
      "id": "694a40bc47af918349188864"
    },
    "timestamp": "2025-12-24T03:35:39.156Z"
  },
  {
    "type": "attendance",
    "data": {
      "customerId": "694a40bc47af918349188864",
      "customerName": "dacchu",
      "date": "2025-12-24",
      "time": "09:05 AM",
      "timestamp": "2025-12-24T03:35:39.129Z",
      "membershipStatus": "active",
      "type": "IN",
      "deviceId": "mock-simulator",
      "_id": "694b5f8b809f662e62ba56d4",
      "createdAt": "2025-12-24T03:35:39.178Z",
      "attendanceId": "att_1766547339179_0eifx6o2j",
      "__v": 0
    },
    "timestamp": "2025-12-24T03:35:39.184Z"
  },
  {
    "type": "customer",
    "data": {
      "_id": "694a40bc47af918349188864",
      "name": "dacchu",
      "age": 20,
      "email": "princevinay4700@gmail.com",
      "phone": "8310268127",
      "plan": "Monthly",
      "validity": "2026-01-23T00:00:00.000Z",
      "notes": "",
      "photo": "",
      "createdBy": "69476926f79a70314966ba12",
      "memberId": "U001",
      "isFirstLogin": true,
      "totalVisits": 9,
      "balance": 0,
      "badgesEarned": [],
      "isInside": false,
      "createdAt": "2025-12-23T07:11:56.885Z",
      "updatedAt": "2025-12-24T12:35:38.016Z",
      "customerId": "cust_1766473917037_4e9zolbjr",
      "__v": 0,
      "lastActivity": "2025-12-24T12:35:38.013Z",
      "status": "active",
      "daysRemaining": 30,
      "id": "694a40bc47af918349188864"
    },
    "timestamp": "2025-12-24T12:35:38.019Z"
  },
  {
    "type": "attendance",
    "data": {
      "customerId": "694a40bc47af918349188864",
      "customerName": "dacchu",
      "date": "2025-12-24",
      "time": "06:05 PM",
      "timestamp": "2025-12-24T12:35:38.013Z",
      "membershipStatus": "active",
      "type": "OUT",
      "deviceId": "mock-simulator",
      "_id": "694bde1af062f9f494fbaff4",
      "createdAt": "2025-12-24T12:35:38.031Z",
      "attendanceId": "att_1766579738031_phapwgk9z",
      "__v": 0
    },
    "timestamp": "2025-12-24T12:35:38.035Z"
  },
  {
    "type": "customer",
    "data": {
      "name": "shakunthala devi",
      "age": 22,
      "email": "edrf@gmail.com",
      "phone": "+911212121212",
      "plan": "Monthly",
      "validity": "2026-01-24T00:00:00.000Z",
      "notes": "",
      "photo": "",
      "createdBy": "69476926f79a70314966ba12",
      "memberId": "U002",
      "password": "$2a$10$hSikhLnhzulZX0Vyt.j3yOJUKbtamQdqLgmxcz8nlCmhTkLGDR6Ny",
      "isFirstLogin": true,
      "totalVisits": 0,
      "balance": 0,
      "badgesEarned": [],
      "isInside": false,
      "_id": "694be85aef4cba5965639927",
      "createdAt": "2025-12-24T13:19:22.805Z",
      "updatedAt": "2025-12-24T13:19:22.805Z",
      "customerId": "cust_1766582362805_iy84vgoo4",
      "__v": 0,
      "status": "active",
      "daysRemaining": 31,
      "id": "694be85aef4cba5965639927"
    },
    "timestamp": "2025-12-24T13:19:22.977Z"
  },
  {
    "type": "payment",
    "data": {
      "customerId": "694be85aef4cba5965639927",
      "customerName": "shakunthala devi",
      "amount": 1000,
      "paymentDate": "2025-12-24T13:19:22.988Z",
      "paymentMethod": "Cash",
      "receiptNumber": "",
      "planType": "Monthly",
      "status": "completed",
      "notes": "",
      "addedBy": "69476926f79a70314966ba12",
      "_id": "694be85aef4cba596563992c",
      "createdAt": "2025-12-24T13:19:22.990Z",
      "updatedAt": "2025-12-24T13:19:22.990Z",
      "paymentId": "pay_1766582362990_xklxskqzu",
      "__v": 0
    },
    "timestamp": "2025-12-24T13:19:22.993Z"
  },
  {
    "type": "customer",
    "data": {
      "_id": "694be85aef4cba5965639927",
      "name": "shakunthala devi",
      "age": 22,
      "email": "edrf@gmail.com",
      "phone": "+911212121212",
      "plan": "Monthly",
      "validity": "2026-01-24T00:00:00.000Z",
      "notes": "",
      "photo": "",
      "createdBy": "69476926f79a70314966ba12",
      "memberId": "U002",
      "isFirstLogin": true,
      "totalVisits": 1,
      "balance": 0,
      "badgesEarned": [],
      "isInside": true,
      "createdAt": "2025-12-24T13:19:22.805Z",
      "updatedAt": "2025-12-24T13:20:46.306Z",
      "customerId": "cust_1766582362805_iy84vgoo4",
      "__v": 0,
      "lastActivity": "2025-12-24T13:20:46.304Z",
      "status": "active",
      "daysRemaining": 31,
      "id": "694be85aef4cba5965639927"
    },
    "timestamp": "2025-12-24T13:20:46.321Z"
  },
  {
    "type": "attendance",
    "data": {
      "customerId": "694be85aef4cba5965639927",
      "customerName": "shakunthala devi",
      "date": "2025-12-24",
      "time": "06:50 PM",
      "timestamp": "2025-12-24T13:20:46.304Z",
      "membershipStatus": "active",
      "type": "IN",
      "deviceId": "mock-simulator",
      "_id": "694be8aeef4cba5965639941",
      "createdAt": "2025-12-24T13:20:46.332Z",
      "attendanceId": "att_1766582446332_821e1ikzr",
      "__v": 0
    },
    "timestamp": "2025-12-24T13:20:46.336Z"
  },
  {
    "type": "customer",
    "data": {
      "_id": "694be85aef4cba5965639927",
      "name": "shakunthala devi",
      "age": 22,
      "email": "edrf@gmail.com",
      "phone": "+911212121212",
      "plan": "Monthly",
      "validity": "2026-01-24T00:00:00.000Z",
      "notes": "",
      "photo": "",
      "createdBy": "69476926f79a70314966ba12",
      "memberId": "U002",
      "isFirstLogin": true,
      "totalVisits": 1,
      "balance": 0,
      "badgesEarned": [],
      "isInside": false,
      "createdAt": "2025-12-24T13:19:22.805Z",
      "updatedAt": "2025-12-24T13:22:15.916Z",
      "customerId": "cust_1766582362805_iy84vgoo4",
      "__v": 0,
      "lastActivity": "2025-12-24T13:22:15.915Z",
      "status": "active",
      "daysRemaining": 31,
      "id": "694be85aef4cba5965639927"
    },
    "timestamp": "2025-12-24T13:22:15.919Z"
  },
  {
    "type": "attendance",
    "data": {
      "customerId": "694be85aef4cba5965639927",
      "customerName": "shakunthala devi",
      "date": "2025-12-24",
      "time": "06:52 PM",
      "timestamp": "2025-12-24T13:22:15.915Z",
      "membershipStatus": "active",
      "type": "OUT",
      "deviceId": "mock-simulator",
      "_id": "694be907ef4cba5965639973",
      "createdAt": "2025-12-24T13:22:15.929Z",
      "attendanceId": "att_1766582535929_743uf065x",
      "__v": 0
    },
    "timestamp": "2025-12-24T13:22:15.932Z"
  },
  {
    "type": "customer",
    "data": {
      "name": "arjun",
      "age": 25,
      "email": "asde@gmail.com",
      "phone": "+914545454545",
      "plan": "Monthly",
      "validity": "2026-01-24T00:00:00.000Z",
      "notes": "",
      "photo": "",
      "createdBy": "69476926f79a70314966ba12",
      "memberId": "U003",
      "password": "$2a$10$oTgHg.9xOLrsLM6QiWjsk.agFRIwnb.EWP/qgR.wv0hyjHZnzVTny",
      "isFirstLogin": true,
      "totalVisits": 0,
      "balance": 0,
      "badgesEarned": [],
      "isInside": false,
      "_id": "694be937ef4cba5965639982",
      "createdAt": "2025-12-24T13:23:03.371Z",
      "updatedAt": "2025-12-24T13:23:03.371Z",
      "customerId": "cust_1766582583371_vhwcw4psw",
      "__v": 0,
      "status": "active",
      "daysRemaining": 31,
      "id": "694be937ef4cba5965639982"
    },
    "timestamp": "2025-12-24T13:23:03.534Z"
  },
  {
    "type": "payment",
    "data": {
      "customerId": "694be937ef4cba5965639982",
      "customerName": "arjun",
      "amount": 1000,
      "paymentDate": "2025-12-24T13:23:03.544Z",
      "paymentMethod": "Cash",
      "receiptNumber": "",
      "planType": "Monthly",
      "status": "completed",
      "notes": "",
      "addedBy": "69476926f79a70314966ba12",
      "_id": "694be937ef4cba5965639987",
      "createdAt": "2025-12-24T13:23:03.546Z",
      "updatedAt": "2025-12-24T13:23:03.546Z",
      "paymentId": "pay_1766582583547_kvnhortog",
      "__v": 0
    },
    "timestamp": "2025-12-24T13:23:03.550Z"
  },
  {
    "type": "customer",
    "data": {
      "_id": "694be937ef4cba5965639982",
      "name": "arjun",
      "age": 25,
      "email": "asde@gmail.com",
      "phone": "+914545454545",
      "plan": "Monthly",
      "validity": "2026-01-24T00:00:00.000Z",
      "notes": "",
      "photo": "",
      "createdBy": "69476926f79a70314966ba12",
      "memberId": "U003",
      "isFirstLogin": true,
      "totalVisits": 1,
      "balance": 0,
      "badgesEarned": [],
      "isInside": true,
      "createdAt": "2025-12-24T13:23:03.371Z",
      "updatedAt": "2025-12-24T13:24:15.494Z",
      "customerId": "cust_1766582583371_vhwcw4psw",
      "__v": 0,
      "lastActivity": "2025-12-24T13:24:15.493Z",
      "status": "active",
      "daysRemaining": 31,
      "id": "694be937ef4cba5965639982"
    },
    "timestamp": "2025-12-24T13:24:15.497Z"
  },
  {
    "type": "attendance",
    "data": {
      "customerId": "694be937ef4cba5965639982",
      "customerName": "arjun",
      "date": "2025-12-24",
      "time": "06:54 PM",
      "timestamp": "2025-12-24T13:24:15.493Z",
      "membershipStatus": "active",
      "type": "IN",
      "deviceId": "mock-simulator",
      "_id": "694be97fef4cba59656399a3",
      "createdAt": "2025-12-24T13:24:15.504Z",
      "attendanceId": "att_1766582655504_43u6ewk7s",
      "__v": 0
    },
    "timestamp": "2025-12-24T13:24:15.507Z"
  },
  {
    "type": "customer",
    "data": {
      "_id": "694be937ef4cba5965639982",
      "name": "arjun",
      "age": 25,
      "email": "asde@gmail.com",
      "phone": "+914545454545",
      "plan": "Monthly",
      "validity": "2025-12-23T00:00:00.000Z",
      "notes": "",
      "photo": "",
      "createdBy": "69476926f79a70314966ba12",
      "memberId": "U003",
      "isFirstLogin": true,
      "totalVisits": 1,
      "balance": 0,
      "badgesEarned": [],
      "isInside": false,
      "createdAt": "2025-12-24T13:23:03.371Z",
      "updatedAt": "2025-12-24T13:25:59.757Z",
      "customerId": "cust_1766582583371_vhwcw4psw",
      "__v": 0,
      "lastActivity": "2025-12-24T13:25:59.755Z",
      "status": "expired",
      "daysRemaining": -1,
      "id": "694be937ef4cba5965639982"
    },
    "timestamp": "2025-12-24T13:25:59.759Z"
  },
  {
    "type": "attendance",
    "data": {
      "customerId": "694be937ef4cba5965639982",
      "customerName": "arjun",
      "date": "2025-12-24",
      "time": "06:55 PM",
      "timestamp": "2025-12-24T13:25:59.755Z",
      "membershipStatus": "expired",
      "type": "OUT",
      "deviceId": "mock-simulator",
      "_id": "694be9e7ef4cba59656399d0",
      "createdAt": "2025-12-24T13:25:59.767Z",
      "attendanceId": "att_1766582759767_5hviwz1bk",
      "__v": 0
    },
    "timestamp": "2025-12-24T13:25:59.769Z"
  },
  {
    "type": "customer",
    "data": {
      "name": "Nuthan",
      "age": 22,
      "email": "email@gmail.com",
      "phone": "1111111111",
      "plan": "Monthly",
      "validity": "2025-12-26T00:00:00.000Z",
      "notes": "",
      "photo": "",
      "createdBy": "69476926f79a70314966ba12",
      "memberId": "U004",
      "password": "$2a$10$25ugaNtdZFGoO9eckqyuWuvdXlOjjKNE8MX7w.KvsH8Ge76st9Cza",
      "isFirstLogin": true,
      "totalVisits": 0,
      "balance": 0,
      "badgesEarned": [],
      "isInside": false,
      "_id": "694bebbb03e5e71ea84ea812",
      "createdAt": "2025-12-24T13:33:47.236Z",
      "updatedAt": "2025-12-24T13:33:47.236Z",
      "customerId": "cust_1766583227237_atz5ykhsd",
      "__v": 0,
      "status": "expiring",
      "daysRemaining": 2,
      "id": "694bebbb03e5e71ea84ea812"
    },
    "timestamp": "2025-12-24T13:33:47.396Z"
  },
  {
    "type": "payment",
    "data": {
      "customerId": "694bebbb03e5e71ea84ea812",
      "customerName": "Nuthan",
      "amount": 1000,
      "paymentDate": "2025-12-24T13:33:47.409Z",
      "paymentMethod": "Cash",
      "receiptNumber": "",
      "planType": "Monthly",
      "status": "completed",
      "notes": "",
      "addedBy": "69476926f79a70314966ba12",
      "_id": "694bebbb03e5e71ea84ea817",
      "createdAt": "2025-12-24T13:33:47.410Z",
      "updatedAt": "2025-12-24T13:33:47.410Z",
      "paymentId": "pay_1766583227411_0ddxbong2",
      "__v": 0
    },
    "timestamp": "2025-12-24T13:33:47.413Z"
  },
  {
    "type": "customer",
    "data": {
      "name": "Sakila",
      "age": 22,
      "email": "asde@gmail.com",
      "phone": "2222222222",
      "plan": "Monthly",
      "validity": "2026-01-25T00:00:00.000Z",
      "notes": "",
      "photo": "",
      "createdBy": "69476926f79a70314966ba12",
      "memberId": "U005",
      "password": "$2a$10$qRB8UnQKjWZlee/Nu4BUX.j/fnVWDfo7lLNqew9ub31n8mOLzMrhm",
      "isFirstLogin": true,
      "totalVisits": 0,
      "balance": 0,
      "badgesEarned": [],
      "isInside": false,
      "_id": "694cae39deb3dacf05a36d9e",
      "createdAt": "2025-12-25T03:23:37.338Z",
      "updatedAt": "2025-12-25T03:23:37.338Z",
      "customerId": "cust_1766633017338_w8nlm18qx",
      "__v": 0,
      "status": "active",
      "daysRemaining": 31,
      "id": "694cae39deb3dacf05a36d9e"
    },
    "timestamp": "2025-12-25T03:23:37.498Z"
  },
  {
    "type": "payment",
    "data": {
      "customerId": "694cae39deb3dacf05a36d9e",
      "customerName": "Sakila",
      "amount": 1000,
      "paymentDate": "2025-12-25T03:23:37.511Z",
      "paymentMethod": "Cash",
      "receiptNumber": "",
      "planType": "Monthly",
      "status": "completed",
      "notes": "",
      "addedBy": "69476926f79a70314966ba12",
      "_id": "694cae39deb3dacf05a36da3",
      "createdAt": "2025-12-25T03:23:37.512Z",
      "updatedAt": "2025-12-25T03:23:37.512Z",
      "paymentId": "pay_1766633017512_l8knb2pzj",
      "__v": 0
    },
    "timestamp": "2025-12-25T03:23:37.515Z"
  },
  {
    "type": "customer",
    "data": {
      "_id": "694cae39deb3dacf05a36d9e",
      "name": "Sakila",
      "age": 22,
      "email": "asde@gmail.com",
      "phone": "2222222222",
      "plan": "Monthly",
      "validity": "2026-01-25T00:00:00.000Z",
      "notes": "",
      "photo": "",
      "createdBy": "69476926f79a70314966ba12",
      "memberId": "U005",
      "isFirstLogin": true,
      "totalVisits": 0,
      "balance": 0,
      "badgesEarned": [],
      "isInside": false,
      "createdAt": "2025-12-25T03:23:37.338Z",
      "updatedAt": "2025-12-25T03:42:51.209Z",
      "customerId": "cust_1766633017338_w8nlm18qx",
      "__v": 0,
      "lastLogin": "2025-12-25T03:42:51.197Z",
      "status": "active",
      "daysRemaining": 31,
      "id": "694cae39deb3dacf05a36d9e"
    },
    "timestamp": "2025-12-25T03:42:51.216Z"
  },
  {
    "type": "customer",
    "data": {
      "_id": "694cae39deb3dacf05a36d9e",
      "name": "Sakila",
      "age": 22,
      "email": "asde@gmail.com",
      "phone": "2222222222",
      "plan": "Monthly",
      "validity": "2026-01-25T00:00:00.000Z",
      "notes": "",
      "photo": "",
      "createdBy": "69476926f79a70314966ba12",
      "memberId": "U005",
      "isFirstLogin": true,
      "totalVisits": 0,
      "balance": 0,
      "badgesEarned": [],
      "isInside": false,
      "createdAt": "2025-12-25T03:23:37.338Z",
      "updatedAt": "2025-12-25T03:45:51.794Z",
      "customerId": "cust_1766633017338_w8nlm18qx",
      "__v": 0,
      "lastLogin": "2025-12-25T03:45:51.792Z",
      "status": "active",
      "daysRemaining": 31,
      "id": "694cae39deb3dacf05a36d9e"
    },
    "timestamp": "2025-12-25T03:45:51.796Z"
  },
  {
    "type": "customer",
    "data": {
      "_id": "694cae39deb3dacf05a36d9e",
      "name": "Sakila",
      "age": 22,
      "email": "asde@gmail.com",
      "phone": "2222222222",
      "plan": "Monthly",
      "validity": "2026-01-25T00:00:00.000Z",
      "notes": "",
      "photo": "",
      "createdBy": "69476926f79a70314966ba12",
      "memberId": "U005",
      "password": "$2a$10$5ERYr1ThkSSwocXYvpXQPOH43wBEuLnfEZzd4ERdkeL/jVNfS/wHi",
      "isFirstLogin": false,
      "totalVisits": 0,
      "balance": 0,
      "badgesEarned": [],
      "isInside": false,
      "createdAt": "2025-12-25T03:23:37.338Z",
      "updatedAt": "2025-12-25T03:46:10.531Z",
      "customerId": "cust_1766633017338_w8nlm18qx",
      "__v": 0,
      "lastLogin": "2025-12-25T03:45:51.792Z",
      "status": "active",
      "daysRemaining": 31,
      "id": "694cae39deb3dacf05a36d9e"
    },
    "timestamp": "2025-12-25T03:46:10.681Z"
  },
  {
    "type": "customer",
    "data": {
      "_id": "694cae39deb3dacf05a36d9e",
      "name": "Sakila",
      "age": 22,
      "email": "asde@gmail.com",
      "phone": "2222222222",
      "plan": "Monthly",
      "validity": "2026-01-25T00:00:00.000Z",
      "notes": "",
      "photo": "",
      "createdBy": "69476926f79a70314966ba12",
      "memberId": "U005",
      "password": "$2a$10$5ERYr1ThkSSwocXYvpXQPOH43wBEuLnfEZzd4ERdkeL/jVNfS/wHi",
      "isFirstLogin": false,
      "totalVisits": 0,
      "balance": 0,
      "badgesEarned": [],
      "isInside": false,
      "createdAt": "2025-12-25T03:23:37.338Z",
      "updatedAt": "2025-12-25T04:07:14.857Z",
      "customerId": "cust_1766633017338_w8nlm18qx",
      "__v": 0,
      "lastLogin": "2025-12-25T04:07:14.856Z",
      "status": "active",
      "daysRemaining": 31,
      "id": "694cae39deb3dacf05a36d9e"
    },
    "timestamp": "2025-12-25T04:07:14.860Z"
  }
]